legendgram/__init__.py
legendgram/__version__.py
legendgram/legendgram.py
legendgram/test_legendgram.py
legendgram/util.py
legendgram-0.0.3.dist-info/DESCRIPTION.rst
legendgram-0.0.3.dist-info/METADATA
legendgram-0.0.3.dist-info/RECORD
legendgram-0.0.3.dist-info/WHEEL
legendgram-0.0.3.dist-info/metadata.json
legendgram-0.0.3.dist-info/top_level.txt
