Metadata-Version: 2.0
Name: legendgram
Version: 0.0.3
Summary: Legendgrams are map legends that visualize the distribution of observations by color in a given map
Home-page: https://github.com/pysal/legendgram
Author: Dani Arribas-Bel, Levi John Wolf
Author-email: daniel.arribas.bel@gmail.com, levi.john.wolf@gmail.com
License: MIT
Platform: UNKNOWN
Classifier: License :: OSI Approved :: BSD License
Classifier: Programming Language :: Python
Classifier: Programming Language :: Python :: 2.7
Classifier: Programming Language :: Python :: 3
Classifier: Programming Language :: Python :: 3.3
Classifier: Programming Language :: Python :: 3.4
Classifier: Programming Language :: Python :: 3.5
Classifier: Programming Language :: Python :: 3.6
Classifier: Programming Language :: Python :: Implementation :: CPython
Requires-Dist: matplotlib
Requires-Dist: numpy
Requires-Dist: palettable
